pytorrentdl/__init__.py
pytorrentdl/cli.py
pytorrentdl/downloader.py
pytorrentdl/session.py
pytorrentdl/torrent_downloader.py
pytorrentdl/torrent_info.py
pytorrentdl-3.0.0.dist-info/LICENSE
pytorrentdl-3.0.0.dist-info/METADATA
pytorrentdl-3.0.0.dist-info/WHEEL
pytorrentdl-3.0.0.dist-info/entry_points.txt
pytorrentdl-3.0.0.dist-info/top_level.txt
pytorrentdl-3.0.0.dist-info/RECORD
