Metadata-Version: 2.1
Name: pytorrentdl
Version: 3.0.0
Summary: Download from torrent with magnet link or .torrent file
Home-page: https://github.com/iw4p/torrentp
Author: Nima Akbarzade
Author-email: iw4p@protonmail.com
License: BSD 2-clause
Classifier: Development Status :: 4 - Beta
Classifier: Intended Audience :: Developers
Classifier: License :: OSI Approved :: BSD License
Classifier: Operating System :: POSIX :: Linux
Classifier: Operating System :: Microsoft :: Windows
Classifier: Programming Language :: Python :: 2.7
Classifier: Programming Language :: Python :: 3
Classifier: Programming Language :: Python :: 3.4
Classifier: Programming Language :: Python :: 3.5
Classifier: Programming Language :: Python :: 3.6
Classifier: Programming Language :: Python :: 3.7
Classifier: Programming Language :: Python :: 3.8
Classifier: Programming Language :: Python :: 3.9
Classifier: Programming Language :: Python :: 3.10
License-File: LICENSE
Requires-Dist: libtorrent >=2.0.7
Requires-Dist: asyncclick >=8.1.7.2
